{ "compressionlevel":-1,
 "height":15,
 "infinite":false,
 "layers":[
  {
   "data":[5, 5, 5, 5, 5, 5, 5, 5, 5, 5, 5, 5, 5, 5, 5, 5, 5, 5, 5, 5, 5, 4, 3, 4, 3, 4, 5, 5, 3, 4, 3, 4, 3, 4, 3, 4, 3, 4, 3, 5, 5, 2, 1, 2, 1, 2, 1, 2, 1, 2, 1, 2, 1, 2, 1, 2, 1, 5, 1, 5, 5, 4, 3, 4, 3, 4, 3, 4, 3, 4, 3, 4, 3, 4, 3, 4, 3, 4, 3, 5, 5, 2, 1, 2, 1, 2, 1, 2, 1, 2, 1, 5, 1, 2, 1, 2, 1, 2, 1, 5, 5, 4, 3, 4, 3, 4, 3, 4, 3, 4, 3, 5, 3, 4, 3, 4, 3, 4, 3, 5, 5, 5, 1, 2, 1, 2, 1, 2, 1, 2, 1, 5, 1, 2, 1, 2, 1, 2, 1, 5, 5, 4, 3, 4, 3, 4, 3, 4, 3, 4, 3, 5, 3, 4, 3, 4, 3, 5, 3, 5, 5, 2, 1, 2, 1, 2, 1, 2, 1, 2, 1, 2, 1, 2, 1, 2, 1, 5, 1, 5, 5, 4, 3, 4, 3, 4, 3, 4, 3, 4, 3, 4, 3, 4, 3, 4, 3, 5, 3, 5, 5, 2, 1, 2, 1, 2, 1, 2, 1, 2, 1, 2, 1, 2, 1, 2, 1, 2, 1, 5, 5, 4, 3, 4, 3, 4, 3, 4, 3, 4, 3, 4, 3, 4, 3, 4, 3, 4, 3, 5, 5, 2, 1, 5, 1, 2, 1, 2, 1, 2, 1, 2, 1, 2, 1, 2, 1, 5, 1, 5, 5, 4, 3, 4, 3, 4, 3, 4, 3, 4, 3, 5, 3, 4, 3, 4, 3, 4, 3, 5, 5, 5, 5, 5, 5, 5, 5, 5, 5, 5, 5, 5, 5, 5, 5, 5, 5, 5, 5, 5],
   "height":15,
   "id":3,
   "name":"fieldMap",
   "opacity":1,
   "type":"tilelayer",
   "visible":true,
   "width":20,
   "x":0,
   "y":0
  },
  {
   "draworder":"topdown",
   "id":9,
   "name":"objects",
   "objects":[
    {
     "height":120,
     "id":10,
     "name":"Snake",
     "rotation":0,
     "type":"Snake",
     "visible":true,
     "width":40,
     "x":360,
     "y":280
    },
    {
     "height":40,
     "id":13,
     "name":"Apple_1",
     "rotation":0,
     "type":"Apple",
     "visible":true,
     "width":40,
     "x":360,
     "y":120
    },
    {
     "height":40,
     "id":17,
     "name":"Apple_2",
     "rotation":0,
     "type":"Apple",
     "visible":true,
     "width":40,
     "x":200,
     "y":200
    },
    {
     "height":40,
     "id":24,
     "name":"Apple_3",
     "rotation":0,
     "type":"Apple",
     "visible":true,
     "width":40,
     "x":560,
     "y":440
    },
    {
     "height":40,
     "id":25,
     "name":"Apple_4",
     "rotation":0,
     "type":"Apple",
     "visible":true,
     "width":40,
     "x":600,
     "y":160
    },
    {
     "height":40,
     "id":26,
     "name":"Apple_6",
     "rotation":0,
     "type":"Apple",
     "visible":true,
     "width":40,
     "x":320,
     "y":480
    },
    {
     "height":40,
     "id":27,
     "name":"Apple_5",
     "rotation":0,
     "type":"Apple",
     "visible":true,
     "width":40,
     "x":160,
     "y":400
    },
    {
     "height":40,
     "id":28,
     "name":"Apple_7",
     "rotation":0,
     "type":"Apple",
     "visible":true,
     "width":40,
     "x":560,
     "y":280
    },
    {
     "height":40,
     "id":29,
     "name":"Apple_8",
     "rotation":0,
     "type":"Apple",
     "visible":true,
     "width":40,
     "x":40,
     "y":40
    },
    {
     "height":40,
     "id":30,
     "name":"Apple_9",
     "rotation":0,
     "type":"Apple",
     "visible":true,
     "width":40,
     "x":720,
     "y":320
    },
    {
     "height":40,
     "id":31,
     "name":"Apple_10",
     "rotation":0,
     "type":"Apple",
     "visible":true,
     "width":40,
     "x":560,
     "y":40
    },
    {
     "height":40,
     "id":32,
     "name":"Coin_1",
     "rotation":0,
     "type":"Coin",
     "visible":true,
     "width":40,
     "x":240,
     "y":400
    },
    {
     "height":40,
     "id":33,
     "name":"Owl",
     "rotation":0,
     "type":"Owl",
     "visible":true,
     "width":40,
     "x":40,
     "y":520
    }],
   "opacity":1,
   "type":"objectgroup",
   "visible":true,
   "x":0,
   "y":0
  }],
 "nextlayerid":10,
 "nextobjectid":34,
 "orientation":"orthogonal",
 "renderorder":"right-down",
 "tiledversion":"1.7.2",
 "tileheight":40,
 "tilesets":[
  {
   "columns":2,
   "firstgid":1,
   "image":"grass.png",
   "imageheight":80,
   "imagewidth":80,
   "margin":0,
   "name":"grass",
   "spacing":0,
   "tilecount":4,
   "tileheight":40,
   "tilewidth":40
  },
  {
   "columns":1,
   "firstgid":5,
   "image":"box1.png",
   "imageheight":40,
   "imagewidth":40,
   "margin":0,
   "name":"box1",
   "spacing":0,
   "tilecount":1,
   "tileheight":40,
   "tilewidth":40
  }],
 "tilewidth":40,
 "type":"map",
 "version":"1.6",
 "width":20
}